README.txt
setup.cfg
setup.py
collective/__init__.py
collective.allowsearch.egg-info/PKG-INFO
collective.allowsearch.egg-info/SOURCES.txt
collective.allowsearch.egg-info/dependency_links.txt
collective.allowsearch.egg-info/entry_points.txt
collective.allowsearch.egg-info/namespace_packages.txt
collective.allowsearch.egg-info/not-zip-safe
collective.allowsearch.egg-info/paster_plugins.txt
collective.allowsearch.egg-info/requires.txt
collective.allowsearch.egg-info/top_level.txt
collective/allowsearch/CHANGELOG
collective/allowsearch/README.txt
collective/allowsearch/__init__.py
collective/allowsearch/adapters.py
collective/allowsearch/configure.zcml
collective/allowsearch/interfaces.py
collective/allowsearch/tests.py
collective/allowsearch/utilities.py
docs/HISTORY.txt
docs/INSTALL.txt
docs/LICENSE.GPL
docs/LICENSE.txt
