Metadata-Version: 1.0
Name: collective.allowsearch
Version: 0.1.4
Summary: Provides an interface and a default adapter to allow users to search the catalog independent of the View permission.
Home-page: https://svn.plone.org/svn/collective/collective.allowsearch/trunk
Author: Stefan Eletzhofer
Author-email: stefan.eletzhofer@inquant.de
License: GPL
Platform: UNKNOWN
Classifier: Framework :: Plone
Classifier: Framework :: Zope2
Classifier: Framework :: Zope3
Classifier: Programming Language :: Python
Classifier: Topic :: Software Development :: Libraries :: Python Modules
